tensorflow_scientific/__init__.py
tensorflow_scientific/version.py
tensorflow_scientific/integrate/__init__.py
tensorflow_scientific/integrate/odes.py
tensorflow_scientific/integrate/tests/__init__.py
tensorflow_scientific/integrate/tests/odes_test.py
tensorflow_scientific/quantum/__init__.py
tensorflow_scientific/quantum/anticommutator.py
tensorflow_scientific/quantum/boson.py
tensorflow_scientific/quantum/cartesian.py
tensorflow_scientific/quantum/cg.py
tensorflow_scientific/quantum/circuitplot.py
tensorflow_scientific/quantum/circuitutils.py
tensorflow_scientific/quantum/commutator.py
tensorflow_scientific/quantum/constants.py
tensorflow_scientific/quantum/dagger.py
tensorflow_scientific/quantum/density.py
tensorflow_scientific/quantum/fermion.py
tensorflow_scientific/quantum/gate.py
tensorflow_scientific/quantum/grover.py
tensorflow_scientific/quantum/hilbert.py
tensorflow_scientific/quantum/identitysearch.py
tensorflow_scientific/quantum/innerproduct.py
tensorflow_scientific/quantum/matrixcache.py
tensorflow_scientific/quantum/matrixutils.py
tensorflow_scientific/quantum/operator.py
tensorflow_scientific/quantum/operatorordering.py
tensorflow_scientific/quantum/operatorset.py
tensorflow_scientific/quantum/pauli.py
tensorflow_scientific/quantum/piab.py
tensorflow_scientific/quantum/qapply.py
tensorflow_scientific/quantum/qasm.py
tensorflow_scientific/quantum/qexpr.py
tensorflow_scientific/quantum/qft.py
tensorflow_scientific/quantum/qubit.py
tensorflow_scientific/quantum/represent.py
tensorflow_scientific/quantum/sho1d.py
tensorflow_scientific/quantum/shor.py
tensorflow_scientific/quantum/spin.py
tensorflow_scientific/quantum/state.py
tensorflow_scientific/quantum/tensorproduct.py
tensorflow_scientific/quantum/tests/__init__.py
tensorflow_scientific/quantum/tests/anticommutator_test.py
tensorflow_scientific/quantum/tests/boson_test.py
tensorflow_scientific/quantum/tests/cartesian_test.py
tensorflow_scientific/quantum/tests/cg_test.py
tensorflow_scientific-0.2.0.dev0.dist-info/LICENSE
tensorflow_scientific-0.2.0.dev0.dist-info/METADATA
tensorflow_scientific-0.2.0.dev0.dist-info/WHEEL
tensorflow_scientific-0.2.0.dev0.dist-info/top_level.txt
tensorflow_scientific-0.2.0.dev0.dist-info/RECORD
