Metadata-Version: 2.1
Name: tensorflow-scientific
Version: 0.2.0.dev0
Summary: Scientific modeling in TensorFlow
Home-page: https://github.com/mukeshmithrakumar/scientific
Author: Mukesh Mithrakumar
Author-email: mukesh@mukeshmithrakumar.com
License: Apache 2.0
Project-URL: Source, https://github.com/mukeshmithrakumar/scientific
Keywords: tensorflow,scientific
Platform: UNKNOWN
Classifier: Development Status :: 3 - Alpha
Classifier: Intended Audience :: Developers
Classifier: Intended Audience :: Education
Classifier: Intended Audience :: Science/Research
Classifier: License :: OSI Approved :: Apache Software License
Classifier: Programming Language :: Python :: 3.5
Classifier: Programming Language :: Python :: 3.6
Classifier: Programming Language :: Python :: 3.7
Classifier: Topic :: Scientific/Engineering :: Mathematics
Classifier: Topic :: Software Development :: Libraries :: Python Modules
Classifier: Topic :: Software Development :: Libraries
Requires-Dist: six (>=1.10.0)
Requires-Dist: tensorflow (==2.0.0-beta0)
